static_markdown/__init__.py
static_markdown/cli.py
static_markdown/document.py
static_markdown/helpers.py
static_markdown/server.py
static_markdown-0.4.0.dist-info/COPYING
static_markdown-0.4.0.dist-info/METADATA
static_markdown-0.4.0.dist-info/WHEEL
static_markdown-0.4.0.dist-info/entry_points.txt
static_markdown-0.4.0.dist-info/top_level.txt
static_markdown-0.4.0.dist-info/RECORD
