Metadata-Version: 2.1
Name: static-markdown
Version: 0.4.0
Summary: A static web server with markdown rendering feature
Home-page: https://github.com/brunobord/static-markdown
Author: Bruno Bord
Author-email: bruno@jehaisleprintemps.net
License: MIT
Keywords: web static markdown
Platform: any
Classifier: Development Status :: 3 - Alpha
Classifier: Intended Audience :: Developers
Classifier: License :: OSI Approved :: MIT License
Classifier: Operating System :: OS Independent
Classifier: Programming Language :: Python
Classifier: Programming Language :: Python :: 3.6
Classifier: Programming Language :: Python :: 3.7
Classifier: Programming Language :: Python :: 3.8
Classifier: Programming Language :: Python :: 3.9
Classifier: Topic :: Software Development :: Libraries :: Python Modules
Classifier: Topic :: Internet :: WWW/HTTP :: HTTP Servers
Requires-Python: >=3.6
Requires-Dist: markdown
Requires-Dist: py-gfm
Requires-Dist: python-slugify
Requires-Dist: loguru
Provides-Extra: dev
Requires-Dist: tox ; extra == 'dev'
Requires-Dist: pytest ; extra == 'dev'
Requires-Dist: requests ; extra == 'dev'
Requires-Dist: pytest-xprocess ; extra == 'dev'
Requires-Dist: black ; extra == 'dev'
Requires-Dist: isort ; extra == 'dev'
Requires-Dist: flake8 ; extra == 'dev'
Provides-Extra: maintain
Requires-Dist: twine ; extra == 'maintain'
